espec_pr3j/__init__.py
espec_pr3j/data_classes.py
espec_pr3j/espec_pr3j.py
espec_pr3j/exceptions.py
espec_pr3j/py.typed
espec_pr3j-0.4.0.dist-info/COPYING.LESSER
espec_pr3j-0.4.0.dist-info/METADATA
espec_pr3j-0.4.0.dist-info/WHEEL
espec_pr3j-0.4.0.dist-info/top_level.txt
espec_pr3j-0.4.0.dist-info/RECORD
