Metadata-Version: 2.1
Name: espec-pr3j
Version: 0.4.0
Summary: Espec PR-3J environmental chamber remote controller
Home-page: https://gitlab.desy.de/leandro.lanzieri/espec_pr3j
Author: Leandro Lanzieri
Author-email: leandro.lanzieri@desy.de
License: MIT
Project-URL: Source, https://gitlab.desy.de/leandro.lanzieri/espec_pr3j
Project-URL: Documentation, https://climate-chamber-leandro-lanzieri-bcc388d1f7cfd484ca00bcced68d65.pages.desy.de
Platform: any
Classifier: Development Status :: 4 - Beta
Classifier: Programming Language :: Python
Requires-Python: >=3.8
License-File: COPYING.LESSER
Requires-Dist: pyvisa
Requires-Dist: pyvisa-py
Provides-Extra: testing
Requires-Dist: setuptools; extra == "testing"
Requires-Dist: pexpect; extra == "testing"
Requires-Dist: pytest; extra == "testing"
Requires-Dist: pytest-cov; extra == "testing"
Requires-Dist: flaky; extra == "testing"
Requires-Dist: pre-commit; extra == "testing"
Requires-Dist: tox; extra == "testing"
Provides-Extra: all
Requires-Dist: inquirer; extra == "all"
